phenixio-0.0.1.dist-info/METADATA
phenixio-0.0.1.dist-info/WHEEL
phenixio-0.0.1.dist-info/entry_points.txt
phenixio-0.0.1.dist-info/licenses/LICENSE
phenixio/__init__.py
phenixio/dev_reader.py
phenixio/reader.py
phenixio-0.0.1.dist-info/RECORD
