Metadata-Version: 2.4
Name: PhenixIO
Version: 0.0.1
Summary: Read images from Revvity (formerly PerkinElmer) Opera Phenix High Content Imager.
Author-Email: Jian Wei Tay <jianweitay@outlook.com>
License-Expression: MIT
License-File: LICENSE
Classifier: Programming Language :: Python :: 3
Classifier: Operating System :: OS Independent
Project-URL: Homepage, https://github.com/BioimageAnalysis/PhenixIO
Project-URL: Issues, https://github.com/BioimageAnalysis/PhenixIO/issues
Requires-Python: >=3.9
